[{"name":"Parque Madrid R\u00edo (Bosque de Trepa)","CP":"28011","location":{"type":"Point","coordinates":[-3.7047360869,40.4204840147]},"place":"park"},{"name":"Jardines de Sabatini","CP":"28013","location":{"type":"Point","coordinates":[-3.7131262383,40.4199537392]},"place":"park"},{"name":"Paseo del Prado","CP":"28014","location":{"type":"Point","coordinates":[-3.6939167976,40.4153094948]},"place":"park"},{"name":"Jardines de las Vistillas","CP":"28005","location":{"type":"Point","coordinates":[-3.7147632723,40.4123433475]},"place":"park"},{"name":"Fuente de Apolo","CP":null,"location":{"type":"Point","coordinates":[-3.6938749192,40.4170329573]},"place":"park"},{"name":"Parque de Madrid","CP":null,"location":{"type":"Point","coordinates":[-3.688675278,40.4166676678]},"place":"park"},{"name":"Plaza de Oriente","CP":"28013","location":{"type":"Point","coordinates":[-3.7121960521,40.4183256684]},"place":"park"},{"name":"Cuesta de Moyano","CP":"28014","location":{"type":"Point","coordinates":[-3.6903131912,40.409644835]},"place":"park"},{"name":"Plaza de la Independencia","CP":"28014","location":{"type":"Point","coordinates":[-3.6881940827,40.4198359201]},"place":"park"},{"name":"Puerta de Espa\u00f1a de los Jardines del Buen Retiro","CP":null,"location":{"type":"Point","coordinates":[-3.6886239351,40.4167089319]},"place":"park"},{"name":"Parque de La Cornisa","CP":"28005","location":{"type":"Point","coordinates":[-3.7149085654,40.4093255739]},"place":"park"},{"name":"Parque Villa de Paris","CP":null,"location":{"type":"Point","coordinates":[-3.6937116895,40.426630527]},"place":"park"},{"name":"Palacio Real de Madrid","CP":"28013","location":{"type":"Point","coordinates":[-3.7142586708,40.4179397201]},"place":"park"},{"name":"Puerta de Murillo de los Jardines del Buen Retiro","CP":null,"location":{"type":"Point","coordinates":[-3.6886020938,40.4128286723]},"place":"park"},{"name":"Plaza de Espa\u00f1a","CP":"28013","location":{"type":"Point","coordinates":[-3.7120163441,40.4235061468]},"place":"park"},{"name":"Plaza de Cibeles","CP":"28014","location":{"type":"Point","coordinates":[-3.6931171835,40.4191912528]},"place":"park"},{"name":"Viaducto de Segovia","CP":"28005","location":{"type":"Point","coordinates":[-3.7135424653,40.4140502032]},"place":"park"},{"name":"Teatro Real de Madrid","CP":"28013","location":{"type":"Point","coordinates":[-3.7110644325,40.418225832]},"place":"park"},{"name":"Plaza del Dos de Mayo","CP":"28004","location":{"type":"Point","coordinates":[-3.7039146778,40.4269219572]},"place":"park"},{"name":"Parque Infantil Plaza De Oriente","CP":null,"location":{"type":"Point","coordinates":[-3.712035,40.417535]},"place":"park"},{"name":"Parque del Casino de La Reina","CP":"28012","location":{"type":"Point","coordinates":[-3.7046964443,40.4060151751]},"place":"park"},{"name":"Jardines de Lepanto","CP":"28013","location":{"type":"Point","coordinates":[-3.7124648778,40.4174087081]},"place":"park"},{"name":"Jardines del cabo Noval","CP":"28013","location":{"type":"Point","coordinates":[-3.7123274803,40.4191649453]},"place":"park"},{"name":"Parque del Emir Mohamed I","CP":"28005","location":{"type":"Point","coordinates":[-3.7147897482,40.4146764283]},"place":"park"},{"name":"Plaza del Olivo","CP":null,"location":{"type":"Point","coordinates":[-3.6970114704,40.4239513581]},"place":"park"},{"name":"Parque Cuesta De La Vega","CP":null,"location":{"type":"Point","coordinates":[-3.7154902842,40.4147849079]},"place":"park"},{"name":"Parque Infantil","CP":null,"location":{"type":"Point","coordinates":[-3.704096854,40.426771941]},"place":"park"},{"name":"Calle Churruca","CP":null,"location":{"type":"Point","coordinates":[-3.7009404503,40.4271690741]},"place":"park"},{"name":"Puerta de Felipe IV","CP":null,"location":{"type":"Point","coordinates":[-3.6887131027,40.4152956063]},"place":"park"},{"name":"Puerta de Atocha del Jardin del Buen Retiro","CP":null,"location":{"type":"Point","coordinates":[-3.6887180564,40.409977059]},"place":"park"},{"name":"Bootcamp Retiro","CP":null,"location":{"type":"Point","coordinates":[-3.688401017,40.4103209542]},"place":"park"}]